itasca/__init__.py
itasca/main.py
pytasca/__init__.py
pytasca/main.py
itasca-2020.7.12.dist-info/LICENSE.txt
itasca-2020.7.12.dist-info/METADATA
itasca-2020.7.12.dist-info/WHEEL
itasca-2020.7.12.dist-info/top_level.txt
itasca-2020.7.12.dist-info/RECORD
