Metadata-Version: 2.1
Name: itasca
Version: 2020.7.12
Summary: Python connectivity for Itasca software
Home-page: https://github.com/jkfurtney/itasca-python
Author: Jason Furtney
Author-email: jkfurtney@gmail.com
License: BSD
Keywords: Itasca,FLAC,FLAC3D,PFC,UDEC,3DEC,PFC2D,PFC3D,FISH
Platform: UNKNOWN
Classifier: Programming Language :: Python :: 2
Classifier: Programming Language :: Python :: 3
Classifier: Development Status :: 5 - Production/Stable
Classifier: License :: OSI Approved :: BSD License
Classifier: Topic :: Scientific/Engineering :: Interface Engine/Protocol Translator
Classifier: Intended Audience :: Science/Research
Requires: numpy
